bbox_align/__init__.py
bbox_align/bounding_box.py
bbox_align/geometry.py
bbox_align/main.py
bbox_align/relationships.py
bbox_align/types.py
bbox_align/utils.py
bbox_align/validations.py
bbox_align-0.2.8.dist-info/METADATA
bbox_align-0.2.8.dist-info/WHEEL
bbox_align-0.2.8.dist-info/licenses/LICENSE
bbox_align-0.2.8.dist-info/RECORD
