Metadata-Version: 2.4
Name: bbox-align
Version: 0.2.8
Summary: A python library that reorders bounding boxes generated by OCR engines into the correct reading order
Project-URL: homepage, https://github.com/doctor-entropy/bbox-align
Project-URL: repository, https://github.com/doctor-entropy/bbox-align
Project-URL: documentation, https://github.com/doctor-entropy/bbox-align
Author-email: Gautham V Reddy <gauthamv93@yahoo.com>
Maintainer-email: Gautham V Reddy <gauthamv93@yahoo.com>
License-File: LICENSE
Keywords: OCR,bounding boxes,document processing,lines,reorder
Requires-Python: >=3.8
